galileo_forecast/__init__.py
galileo_forecast/_thompson_sampler_old.py
galileo_forecast/colors.py
galileo_forecast/data_samplers.py
galileo_forecast/galileo_plots/__init__.py
galileo_forecast/galileo_plots/bin_freq_spread_plot.py
galileo_forecast/galileo_plots/plot_utils.py
galileo_forecast/galileo_plots/plotprotocol.py
galileo_forecast/galileo_plots/single_instance_plot.py
galileo_forecast/model.py
galileo_forecast/pre_trained_thompson_sampler.py
galileo_forecast/thompson_sampler.py
galileo_forecast-0.1.4.dist-info/METADATA
galileo_forecast-0.1.4.dist-info/WHEEL
galileo_forecast-0.1.4.dist-info/RECORD
