Metadata-Version: 2.1
Name: galileo-forecast
Version: 0.1.4
Summary: Thompson Sampling using bootstrap sampling
Author: Niels Ota
Author-email: ota.niels@bcg.com
Requires-Python: >=3.10,<4.0
Classifier: Programming Language :: Python :: 3
Classifier: Programming Language :: Python :: 3.10
Classifier: Programming Language :: Python :: 3.11
Requires-Dist: lightgbm (>=4.5.0,<5.0.0)
Requires-Dist: matplotlib (>=3.9.2,<4.0.0)
Requires-Dist: nbformat (>=5.10.4,<6.0.0)
Requires-Dist: numpy (>=2.1.1,<3.0.0)
Requires-Dist: pandas (>=2.2.3,<3.0.0)
Requires-Dist: plotly (>=5.24.1,<6.0.0)
Requires-Dist: pydantic (>=2.9.2,<3.0.0)
Requires-Dist: scikit-learn (>=1.5.2,<2.0.0)
Requires-Dist: xgboost (>=2.1.1,<3.0.0)
